Metadata-Version: 2.1
Name: instantdirect
Version: 3.0
Summary: an automation software 
Author: jack
Author-email: kinginjack@gmail.com
License: GPL-3.0
Platform: UNKNOWN
Requires-Python: >=3.8
